nimble_llm_caller/__init__.py
nimble_llm_caller/compatibility.py
nimble_llm_caller/exceptions.py
nimble_llm_caller/core/config_manager.py
nimble_llm_caller/core/content_chunker.py
nimble_llm_caller/core/content_generator.py
nimble_llm_caller/core/context_analyzer.py
nimble_llm_caller/core/context_strategy.py
nimble_llm_caller/core/document_assembler.py
nimble_llm_caller/core/enhanced_caller.py
nimble_llm_caller/core/enhanced_llm_caller.py
nimble_llm_caller/core/file_processor.py
nimble_llm_caller/core/interaction_logger.py
nimble_llm_caller/core/llm_caller.py
nimble_llm_caller/core/model_capacity_registry.py
nimble_llm_caller/core/model_upshifter.py
nimble_llm_caller/core/prompt_manager.py
nimble_llm_caller/core/token_estimator.py
nimble_llm_caller/models/context_config.py
nimble_llm_caller/models/request.py
nimble_llm_caller/models/response.py
nimble_llm_caller/utils/json_parser.py
nimble_llm_caller/utils/retry_strategy.py
nimble_llm_caller-0.2.2.dist-info/METADATA
nimble_llm_caller-0.2.2.dist-info/WHEEL
nimble_llm_caller-0.2.2.dist-info/top_level.txt
nimble_llm_caller-0.2.2.dist-info/RECORD
