Metadata-Version: 2.4
Name: nimble-llm-caller
Version: 0.2.2
Summary: A robust, multi-model LLM calling package with intelligent context management, file processing, and advanced prompt handling
Author-email: Nimble Books LLC <info@nimblebooks.com>
License-Expression: MIT
Project-URL: Homepage, https://github.com/nimblebooks/nimble-llm-caller
Project-URL: Documentation, https://nimble-llm-caller.readthedocs.io
Project-URL: Repository, https://github.com/nimblebooks/nimble-llm-caller
Project-URL: Issues, https://github.com/nimblebooks/nimble-llm-caller/issues
Keywords: llm,ai,openai,anthropic,google,prompt,batch,document,context-management,file-processing,token-estimation,model-upshifting
Classifier: Development Status :: 4 - Beta
Classifier: Intended Audience :: Developers
Classifier: Programming Language :: Python :: 3
Classifier: Programming Language :: Python :: 3.9
Classifier: Programming Language :: Python :: 3.10
Classifier: Programming Language :: Python :: 3.11
Classifier: Programming Language :: Python :: 3.12
Classifier: Topic :: Software Development :: Libraries :: Python Modules
Classifier: Topic :: Scientific/Engineering :: Artificial Intelligence
Requires-Python: >=3.9
Requires-Dist: litellm>=1.0.0
Requires-Dist: python-dotenv>=1.0.0
Requires-Dist: json-repair>=0.25.0
Requires-Dist: jinja2>=3.1.0
Requires-Dist: pydantic>=2.0.0
Requires-Dist: typing-extensions>=4.0.0
Requires-Dist: tiktoken>=0.5.0
Requires-Dist: pytest>=8.4.1
Requires-Dist: pytest-cov>=6.2.1
Requires-Dist: pandoc>=2.4
Requires-Dist: tomli>=2.2.1
Requires-Dist: streamlit>=1.48.1
Requires-Dist: build>=1.3.0
Requires-Dist: twine>=6.1.0
Provides-Extra: enhanced
Requires-Dist: PyPDF2>=3.0.0; extra == "enhanced"
Requires-Dist: pdfplumber>=0.9.0; extra == "enhanced"
Requires-Dist: python-docx>=0.8.11; extra == "enhanced"
Requires-Dist: striprtf>=0.0.26; extra == "enhanced"
Requires-Dist: Pillow>=9.0.0; extra == "enhanced"
Requires-Dist: openpyxl>=3.0.0; extra == "enhanced"
Requires-Dist: anthropic>=0.25.0; extra == "enhanced"
Requires-Dist: google-generativeai>=0.3.0; extra == "enhanced"
Requires-Dist: PyYAML>=6.0.0; extra == "enhanced"
Provides-Extra: all
Requires-Dist: nimble-llm-caller[enhanced]; extra == "all"
Provides-Extra: dev
Requires-Dist: pytest>=7.0.0; extra == "dev"
Requires-Dist: pytest-asyncio>=0.21.0; extra == "dev"
Requires-Dist: pytest-cov>=4.0.0; extra == "dev"
Requires-Dist: black>=23.0.0; extra == "dev"
Requires-Dist: isort>=5.12.0; extra == "dev"
Requires-Dist: flake8>=6.0.0; extra == "dev"
Requires-Dist: mypy>=1.0.0; extra == "dev"
Requires-Dist: pytest-mock>=3.10.0; extra == "dev"
Requires-Dist: pytest-xdist>=3.0.0; extra == "dev"
Provides-Extra: docs
Requires-Dist: mkdocs>=1.5.0; extra == "docs"
Requires-Dist: mkdocs-material>=9.0.0; extra == "docs"
Requires-Dist: mkdocstrings[python]>=0.22.0; extra == "docs"
